geventactor/__init__.py
geventactor/publisher.py
geventactor/actor.py
processactor/__init__.py
processactor/publisher.py
processactor/actor.py
threadactor/__init__.py
threadactor/publisher.py
threadactor/actor.py
zmqactor/__init__.py
zmqactor/actor.py
actorfactory/__init__.py
actorfactory/factory.py
pyactors_ng-0.5.dist-info/top_level.txt
pyactors_ng-0.5.dist-info/dependency_links.txt
pyactors_ng-0.5.dist-info/METADATA
pyactors_ng-0.5.dist-info/DESCRIPTION.rst
pyactors_ng-0.5.dist-info/metadata.json
pyactors_ng-0.5.dist-info/WHEEL
pyactors_ng-0.5.dist-info/RECORD
